{"meta":{"title":"Using WireGuard to create a network overlay","intro":"You can create an overlay network between your runner and a service in your private network.","product":"GitHub Actions","breadcrumbs":[{"href":"/en/actions","title":"GitHub Actions"},{"href":"/en/actions/how-tos","title":"How-tos"},{"href":"/en/actions/how-tos/manage-runners","title":"Manage runners"},{"href":"/en/actions/how-tos/manage-runners/github-hosted-runners","title":"GitHub-hosted runners"},{"href":"/en/actions/how-tos/manage-runners/github-hosted-runners/connect-to-a-private-network","title":"Connect to a private network"},{"href":"/en/actions/how-tos/manage-runners/github-hosted-runners/connect-to-a-private-network/connect-with-wireguard","title":"Connect with WireGuard"}],"documentType":"article"},"body":"# Using WireGuard to create a network overlay\n\nYou can create an overlay network between your runner and a service in your private network.\n\n## Using WireGuard to create a network overlay\n\nIf you don't want to maintain separate infrastructure for an API Gateway, you can create an overlay network between your runner and a service in your private network, by running WireGuard in both places.\n\nThere are various disadvantages to this approach:\n\n* To reach WireGuard running on your private service, you will need a well-known IP address and port that your workflow can reference: this can either be a public IP address and port, a port mapping on a network gateway, or a service that dynamically updates DNS.\n* WireGuard doesn't handle NAT traversal out of the box, so you'll need to identify a way to provide this service.\n* This connection is one-to-one, so if you need high availability or high throughput you'll need to build that on top of WireGuard.\n* You'll need to generate and securely store keys for both the runner and your private service. WireGuard uses UDP, so your network must support UDP traffic.\n\nThere are some advantages too, as you can run WireGuard on an existing server so you don't have to maintain separate infrastructure, and it's well supported on GitHub-hosted runners.\n\n## Example: Configuring WireGuard\n\nThis example workflow configures WireGuard to connect to a private service.\n\nFor this example, the WireGuard instance running in the private network has this configuration:\n\n* Overlay network IP address of `192.168.1.1`\n* Public IP address and port of `1.2.3.4:56789`\n* Public key `examplepubkey1234...`\n\nThe WireGuard instance in the GitHub Actions runner has this configuration:\n\n* Overlay network IP address of `192.168.1.2`\n* Private key stores as an GitHub Actions secret under `WIREGUARD_PRIVATE_KEY`\n\n```yaml\nname: WireGuard example\n\non:\n  workflow_dispatch:\n\njobs:\n  wireguard_example:\n    runs-on: ubuntu-latest\n    steps:\n      - run: sudo apt install wireguard\n\n      - run: echo \"${{ secrets.WIREGUARD_PRIVATE_KEY }}\" > privatekey\n\n      - run: sudo ip link add dev wg0 type wireguard\n\n      - run: sudo ip address add dev wg0 192.168.1.2 peer 192.168.1.1\n\n      - run: sudo wg set wg0 listen-port 48123 private-key privatekey peer examplepubkey1234... allowed-ips 0.0.0.0/0 endpoint 1.2.3.4:56789\n\n      - run: sudo ip link set up dev wg0\n\n      - run: curl -vvv http://192.168.1.1\n```\n\nFor more information, see [WireGuard's Quick Start](https://www.wireguard.com/quickstart/), as well as [Using secrets in GitHub Actions](/en/actions/security-guides/using-secrets-in-github-actions) for how to securely store keys.\n\n### Using Tailscale to create a network overlay\n\nTailscale is a commercial product built on top of WireGuard. This option is very similar to WireGuard, except Tailscale is more of a complete product experience instead of an open source component.\n\nIts disadvantages are similar to WireGuard: The connection is one-to-one, so you might need to do additional work for high availability or high throughput. You still need to generate and securely store keys. The protocol is still UDP, so your network must support UDP traffic.\n\nHowever, there are some advantages over WireGuard: NAT traversal is built-in, so you don't need to expose a port to the public internet. It is by far the quickest of these options to get up and running, since Tailscale provides an GitHub Actions workflow with a single step to connect to the overlay network.\n\nFor more information, see the [Tailscale GitHub Action](https://github.com/tailscale/github-action), as well as [Using secrets in GitHub Actions](/en/actions/security-guides/using-secrets-in-github-actions) for how to securely store keys."}