{"meta":{"title":"Deploying Java to Azure App Service","intro":"Learn how to deploy a Java project to Azure App Service as part of your continuous deployment (CD) workflows.","product":"GitHub Actions","breadcrumbs":[{"href":"/en/actions","title":"GitHub Actions"},{"href":"/en/actions/how-tos","title":"How-tos"},{"href":"/en/actions/how-tos/deploy","title":"Deploy"},{"href":"/en/actions/how-tos/deploy/deploy-to-third-party-platforms","title":"Deploy to third-party platforms"},{"href":"/en/actions/how-tos/deploy/deploy-to-third-party-platforms/java-to-azure-app-service","title":"Java to Azure App Service"}],"documentType":"article"},"body":"# Deploying Java to Azure App Service\n\nLearn how to deploy a Java project to Azure App Service as part of your continuous deployment (CD) workflows.\n\n## Prerequisites\n\nBefore creating your GitHub Actions workflow, you will first need to complete the following setup steps:\n\n1. Create an Azure App Service plan.\n\n   For example, you can use the Azure CLI to create a new App Service plan:\n\n   ```bash copy\n   az appservice plan create \\\n      --resource-group MY_RESOURCE_GROUP \\\n      --name MY_APP_SERVICE_PLAN \\\n      --is-linux\n   ```\n\n   In the command above, replace `MY_RESOURCE_GROUP` with your pre-existing Azure Resource Group, and `MY_APP_SERVICE_PLAN` with a new name for the App Service plan.\n\n   See the Azure documentation for more information on using the [Azure CLI](https://docs.microsoft.com/cli/azure/):\n\n   * For authentication, see [Sign in with Azure CLI](https://docs.microsoft.com/cli/azure/authenticate-azure-cli).\n   * If you need to create a new resource group, see [az group](https://docs.microsoft.com/cli/azure/group?view=azure-cli-latest#az_group_create).\n\n2. Create a web app.\n\n   For example, you can use the Azure CLI to create an Azure App Service web app with a Java runtime:\n\n   ```bash copy\n   az webapp create \\\n       --name MY_WEBAPP_NAME \\\n       --plan MY_APP_SERVICE_PLAN \\\n       --resource-group MY_RESOURCE_GROUP \\\n       --runtime \"JAVA|11-java11\"\n   ```\n\n   In the command above, replace the parameters with your own values, where `MY_WEBAPP_NAME` is a new name for the web app.\n\n3. Configure an Azure publish profile and create an `AZURE_WEBAPP_PUBLISH_PROFILE` secret.\n\n   Generate your Azure deployment credentials using a publish profile. For more information, see [Generate deployment credentials](https://docs.microsoft.com/azure/app-service/deploy-github-actions?tabs=applevel#generate-deployment-credentials) in the Azure documentation.\n\n   In your GitHub repository, create a secret named `AZURE_WEBAPP_PUBLISH_PROFILE` that contains the contents of the publish profile. For more information on creating secrets, see [Using secrets in GitHub Actions](/en/actions/security-guides/using-secrets-in-github-actions#creating-secrets-for-a-repository).\n\n4. Optionally, configure a deployment environment. Environments are used to describe a general deployment target like `production`, `staging`, or `development`. When a GitHub Actions workflow deploys to an environment, the environment is displayed on the main page of the repository. You can use environments to require approval for a job to proceed, restrict which branches can trigger a workflow, gate deployments with custom deployment protection rules, or limit access to secrets. For more information about creating environments, see [Managing environments for deployment](/en/actions/deployment/targeting-different-environments/managing-environments-for-deployment).\n\n## Creating the workflow\n\nOnce you've completed the prerequisites, you can proceed with creating the workflow.\n\nThe following example workflow demonstrates how to build and deploy a Java project to Azure App Service when there is a push to the `main` branch.\n\nEnsure that you set `AZURE_WEBAPP_NAME` in the workflow `env` key to the name of the web app you created. If you want to use a Java version other than `11`, change `JAVA_VERSION`.\n\nIf you configured a deployment environment, change the value of `environment` to be the name of your environment. If you did not configure an environment or if your workflow is in a private repository and you do not use GitHub Enterprise Cloud, delete the `environment` key.\n\n```yaml copy\n# This workflow uses actions that are not certified by GitHub.\n# They are provided by a third-party and are governed by\n# separate terms of service, privacy policy, and support\n# documentation.\n\n# GitHub recommends pinning actions to a commit SHA.\n# To get a newer version, you will need to update the SHA.\n# You can also reference a tag or branch, but the action may change without warning.\n\nname: Build and deploy JAR app to Azure Web App\n\nenv:\n  AZURE_WEBAPP_NAME: MY_WEBAPP_NAME   # set this to your application's name\n  JAVA_VERSION: '11'                  # set this to the Java version to use\n\non:\n  push:\n    branches:\n      - main\n\njobs:\n  build:\n    runs-on: ubuntu-latest\n\n    steps:\n      - uses: actions/checkout@v5\n\n      - name: Set up Java version\n        uses: actions/setup-java@v4\n        with:\n          java-version: ${{ env.JAVA_VERSION }}\n          cache: 'maven'\n\n      - name: Build with Maven\n        run: mvn clean install\n\n      - name: Upload artifact for deployment job\n        uses: actions/upload-artifact@v4\n        with:\n          name: java-app\n          path: '${{ github.workspace }}/target/*.jar'\n\n  deploy:\n    runs-on: ubuntu-latest\n    needs: build\n    environment:\n      name: 'production'\n      url: ${{ steps.deploy-to-webapp.outputs.webapp-url }}\n\n    steps:\n      - name: Download artifact from build job\n        uses: actions/download-artifact@v5\n        with:\n          name: java-app\n\n      - name: Deploy to Azure Web App\n        id: deploy-to-webapp\n        uses: azure/webapps-deploy@85270a1854658d167ab239bce43949edb336fa7c\n        with:\n          app-name: ${{ env.AZURE_WEBAPP_NAME }}\n          publish-profile: ${{ secrets.AZURE_WEBAPP_PUBLISH_PROFILE }}\n          package: '*.jar'\n```\n\n## Further reading\n\n* For the original workflow template, see [`azure-webapps-java-jar.yml`](https://github.com/actions/starter-workflows/blob/main/deployments/azure-webapps-java-jar.yml) in the GitHub Actions `starter-workflows` repository.\n* The action used to deploy the web app is the official Azure [`Azure/webapps-deploy`](https://github.com/Azure/webapps-deploy) action.\n* For more examples of GitHub Action workflows that deploy to Azure, see the [actions-workflow-samples](https://github.com/Azure/actions-workflow-samples) repository."}